qatiumsdk/__init__.py
qatiumsdk/assets/__init__.py
qatiumsdk/assets/base.py
qatiumsdk/assets/common.py
qatiumsdk/assets/junction.py
qatiumsdk/assets/pipe.py
qatiumsdk/assets/pump.py
qatiumsdk/assets/supply_source.py
qatiumsdk/assets/tank.py
qatiumsdk/assets/valve.py
qatiumsdk/commands.py
qatiumsdk/geojson.py
qatiumsdk/integrations.py
qatiumsdk/map.py
qatiumsdk/network.py
qatiumsdk/plugin.py
qatiumsdk/readings.py
qatiumsdk/register_plugin.py
qatiumsdk/sdk.py
qatiumsdk/sdk_version.py
qatiumsdk/secrets.py
qatiumsdk/types.py
qatiumsdk/ui.py
qatiumsdk/zone.py
qatiumsdk-0.0.60.dist-info/METADATA
qatiumsdk-0.0.60.dist-info/WHEEL
qatiumsdk-0.0.60.dist-info/RECORD
